shippy/__init__.py
shippy/auth.py
shippy/core.py
shippy/fhirclient.py
shippy/http.py
shippy/kite.py
ume_shippy-0.0.11.dist-info/LICENSE
ume_shippy-0.0.11.dist-info/METADATA
ume_shippy-0.0.11.dist-info/WHEEL
ume_shippy-0.0.11.dist-info/RECORD
