Metadata-Version: 2.1
Name: ume-shippy
Version: 0.0.11
Summary: A library with helper functions for the Smart Hospital Information Platform (SHIP)
Home-page: https://github.com/UMEssen/shippy
License: MIT
Author: Felix Nensa
Author-email: felix.nensa@uk-essen.de
Requires-Python: >=3.12
Classifier: License :: OSI Approved :: MIT License
Classifier: Programming Language :: Python :: 3
Classifier: Programming Language :: Python :: 3.12
Classifier: Programming Language :: Python :: 3.13
Requires-Dist: aiohttp (>=3.11.11,<4.0.0)
Requires-Dist: chardet (>=5.2.0,<6.0.0)
Requires-Dist: charset-normalizer (>=3.4.1,<4.0.0)
Requires-Dist: huggingface-hub (>=0.27.0,<0.28.0)
Requires-Dist: requests (>=2.32.3,<3.0.0)
